LAMMPyS/__init__.py
LAMMPyS/dump.py
LAMMPyS/group.py
LAMMPyS/subclass.py
LAMMPyS/sv.py
LAMMPyS/test.py
LAMMPyS/voronoi.py
LAMMPyS-2.4.2.dist-info/DESCRIPTION.rst
LAMMPyS-2.4.2.dist-info/LICENSE.txt
LAMMPyS-2.4.2.dist-info/METADATA
LAMMPyS-2.4.2.dist-info/RECORD
LAMMPyS-2.4.2.dist-info/WHEEL
LAMMPyS-2.4.2.dist-info/metadata.json
LAMMPyS-2.4.2.dist-info/top_level.txt
